[
    {
        "titulo": "Queijos",
        "id": 1,
        "itens": [
            {
                "categoria": "Queijos Suaves",
                "banner":"/imagens/galeria/foto-1.jpeg",
                "subitens": [
                    {"nome": "Queijo mussarela"},
                    {"nome": "Queijo prato"}
                ]
            },
            {
                "categoria": "Queijo Fortes",
                "banner":"/imagens/galeria/foto-2.jpeg",
                "subitens": [
                    {"nome": "Queijo Gorgonzola"},
                    {"nome": "Queijo"}
                ]
            },
            {
                "categoria": "Queijo Branco",
                "banner":"url",
                "subitens": [
                    {"nome": "Queijo Branco 1"},
                    {"nome": "Queijo Branco 2"}
                ]
            }
        ]
    },
    {
        "titulo": "Doces",
        "id": 2,
        "itens": [
            {
                "categoria": "Potes",
                "banner":"/imagens/galeria/docePoteBanner.jpeg",
                "subitens": [
                    {"nome": "Doce de geleia"},
                    {"nome": "Doce de leite"},
                    {"nome": "Doce de Coco"},
                    {"nome": "Doce de Cocada Cremosa"}
                ]
            },
            {
                "categoria": "Barras",
                "banner":"/imagens/galeria/bannerDoceBarra.jpeg",
                "subitens": [
                    {"nome": "Doce de leite"},
                    {"nome": "Cocada"},
                    {"nome": "Rapadura"}
                ]
            },
            {
                "categoria": "Diets",
                "banner":"url",
                "subitens": [
                    {"nome": "Doce de banana"},
                    {"nome": "Queijo Branco 2"}
                ]
            }
        ]
    },
    {
        "titulo": "Temperos",
        "id": 3,
        "itens": []
    },
    {
        "titulo": "Aperitivos",
        "id": 4,
        "itens": []
    }
]
